CHANGELOG.rst
LICENSE.txt
MANIFEST.in
README.rst
TODO.txt
VERSION.txt
setup.cfg
setup.py
test-requirements.txt
fso/__init__.py
fso/api.py
fso/filesystemoverlay.py
fso/test_api.py
fso/test_filesystemoverlay.py
fso.egg-info/PKG-INFO
fso.egg-info/SOURCES.txt
fso.egg-info/dependency_links.txt
fso.egg-info/requires.txt
fso.egg-info/top_level.txt
fso.egg-info/zip-safe