Metadata-Version: 1.1
Name: fso
Version: 0.3.2
Summary: File System Overlay - filesystem layering for unit testing
Home-page: http://github.com/metagriffin/fso
Author: metagriffin
Author-email: mg.pypi@uberdev.org
License: GPLv3+
Keywords: unit testing file system open read write layering protection
Platform: any
Classifier: Development Status :: 4 - Beta
Classifier: Intended Audience :: Developers
Classifier: Programming Language :: Python
Classifier: Operating System :: OS Independent
Classifier: Natural Language :: English
Classifier: License :: OSI Approved :: GNU General Public License v3 or later (GPLv3+)
